galfitools/__init__.py
galfitools/config/__init__.py
galfitools/config/default.conv
galfitools/config/default.nnw
galfitools/config/default.sex
galfitools/config/sex.param
galfitools/galin/MakeMask.py
galfitools/galin/MakePSF.py
galfitools/galin/MaskDs9.py
galfitools/galin/MaskSky.py
galfitools/galin/__init__.py
galfitools/galin/checkGalFile.py
galfitools/galin/galfit.py
galfitools/galin/getBoxSizeDs9.py
galfitools/galin/getSersic.py
galfitools/galin/getStar.py
galfitools/galin/imarith.py
galfitools/galin/initgal.py
galfitools/galin/std.py
galfitools/galin/xy2fits.py
galfitools/galout/PhotDs9.py
galfitools/galout/__init__.py
galfitools/galout/fitlog2csv.py
galfitools/galout/getBT.py
galfitools/galout/getBarSize.py
galfitools/galout/getCOW.py
galfitools/galout/getMeRad.py
galfitools/galout/getMissingLight.py
galfitools/galout/getN.py
galfitools/galout/getPeak.py
galfitools/galout/getRads.py
galfitools/galout/showcube.py
galfitools/mge/SbProf.py
galfitools/mge/__init__.py
galfitools/mge/mge2galfit.py
galfitools/shell/__init__.py
galfitools/shell/commands_galin.py
galfitools/shell/commands_galout.py
galfitools/shell/commands_mge.py
galfitools/shell/commands_sim.py
galfitools/shell/commands_sky.py
galfitools/shell/prt.py
galfitools/sim/MakeSim.py
galfitools/sim/__init__.py
galfitools/sky/GalfitSky.py
galfitools/sky/SkyDs9.py
galfitools/sky/SkyRing.py
galfitools/sky/__init__.py
galfitools-1.18.0.dist-info/licenses/LICENSE.txt
galfitools-1.18.0.dist-info/METADATA
galfitools-1.18.0.dist-info/WHEEL
galfitools-1.18.0.dist-info/entry_points.txt
galfitools-1.18.0.dist-info/top_level.txt
galfitools-1.18.0.dist-info/RECORD
