Metadata-Version: 2.4
Name: GALFITools
Version: 1.18.0
Summary: A library for GALFIT package
Home-page: https://github.com/canorve/GALFITools
Author: Christopher Añorve
Author-email: canorve@gmail.com
License: MIT
Project-URL: Documentation, https://pyscaffold.org/
Project-URL: Source, https://github.com/canorve/GALFITools
Project-URL: GALFIT, https://users.obs.carnegiescience.edu/peng/work/galfit/galfit.html
Platform: Mac
Platform: Linux
Classifier: Development Status :: 4 - Beta
Classifier: Programming Language :: Python
Classifier: Development Status :: 5 - Production/Stable
Classifier: Framework :: Pytest
Classifier: Intended Audience :: Science/Research
Classifier: License :: OSI Approved :: MIT License
Classifier: Natural Language :: Spanish
Classifier: Natural Language :: English
Classifier: Topic :: Scientific/Engineering :: Astronomy
Classifier: Programming Language :: Python :: 3.9
Classifier: Programming Language :: Python :: 3.10
Classifier: Programming Language :: Python :: 3.11
Classifier: Programming Language :: Python :: 3.12
Classifier: Programming Language :: Python :: 3.13
Requires-Python: >=3.9
License-File: LICENSE.txt
Requires-Dist: importlib-metadata; python_version < "3.8"
Requires-Dist: numpy>=1.22.4
Requires-Dist: astropy>=5.1
Requires-Dist: matplotlib>=3.5.2
Requires-Dist: scipy>=1.9.1
Requires-Dist: mgefit>=5.0.13
Requires-Dist: pre-commit>=2.18.1
Provides-Extra: testing
Requires-Dist: setuptools; extra == "testing"
Requires-Dist: pytest; extra == "testing"
Requires-Dist: pytest-cov; extra == "testing"
Dynamic: license-file
